gpalib/__init__.py
gpalib/arithmetic.py
gpalib-0.1.5.dist-info/LICENSE
gpalib-0.1.5.dist-info/METADATA
gpalib-0.1.5.dist-info/WHEEL
gpalib-0.1.5.dist-info/top_level.txt
gpalib-0.1.5.dist-info/RECORD
