Metadata-Version: 2.1
Name: gpalib
Version: 0.1.5
Summary: A library to convert scores using many arithmetics
Home-page: https://github.com/billchenchina/hitutil
Author: inclyc
Author-email: axoford@icloud.com
License: UNKNOWN
Project-URL: Bug Reports, https://github.com/billchenchina/hitutil/issues
Project-URL: Source, https://github.com/billchenchina/hitutil/
Keywords: GPA
Platform: UNKNOWN
Classifier: Development Status :: 2 - Pre-Alpha
Classifier: Intended Audience :: Developers
Classifier: License :: OSI Approved :: Apache Software License
Classifier: Natural Language :: Chinese (Simplified)
Classifier: Natural Language :: English
Classifier: Operating System :: MacOS
Classifier: Operating System :: Microsoft :: Windows
Classifier: Operating System :: POSIX :: Linux
Classifier: Programming Language :: Python :: 3
Classifier: Programming Language :: Python :: 3.7
Classifier: Programming Language :: Python :: 3.8
Classifier: Programming Language :: Python :: 3.9
Classifier: Programming Language :: Python :: 3 :: Only
Classifier: Topic :: Utilities
Requires-Python: >=3.5, <4
